process_manager/__init__.py
python_process_manager-0.0.2.dist-info/LICENSE
python_process_manager-0.0.2.dist-info/METADATA
python_process_manager-0.0.2.dist-info/WHEEL
python_process_manager-0.0.2.dist-info/entry_points.txt
python_process_manager-0.0.2.dist-info/top_level.txt
python_process_manager-0.0.2.dist-info/RECORD
