Metadata-Version: 2.1
Name: python-process-manager
Version: 0.0.2
Summary: Python Process Manager: Python process manager: Dispatch (ssh/bash) & control (zmq) detached (remote) processes
Home-page: https://github.com/larsrollik/python_process_manager
Author: Lars B. Rollik
Author-email: L.B.Rollik@protonmail.com
License: BSD 3-Clause License
Project-URL: Issue Tracker, https://github.com/larsrollik/python_process_manager/issues
Platform: UNKNOWN
Classifier: Programming Language :: Python :: 3
Classifier: License :: OSI Approved :: BSD License
Classifier: Operating System :: OS Independent
Requires-Python: >=3.6
License-File: LICENSE
Requires-Dist: black
Provides-Extra: dev
Requires-Dist: black ; extra == 'dev'
Requires-Dist: pytest-cov ; extra == 'dev'
Requires-Dist: pytest ; extra == 'dev'
Requires-Dist: gitpython ; extra == 'dev'
Requires-Dist: bump2version ; extra == 'dev'
Requires-Dist: pre-commit ; extra == 'dev'
Requires-Dist: flake8 ; extra == 'dev'
